boneflet-0.1.1.dist-info/METADATA
boneflet-0.1.1.dist-info/WHEEL
boneflet/__init__.py
boneflet/bonetools.py
boneflet/button.py
boneflet/demo.py
boneflet/plugins/__init__.py
boneflet/plugins/demo.py
boneflet/plugins/ui_demo.py
boneflet/tab.py
boneflet-0.1.1.dist-info/RECORD
